LICENSE
README.md
setup.py
hushh_ai/__init__.py
hushh_ai/llm.py
hushhai.egg-info/PKG-INFO
hushhai.egg-info/SOURCES.txt
hushhai.egg-info/dependency_links.txt
hushhai.egg-info/requires.txt
hushhai.egg-info/top_level.txt