Metadata-Version: 2.1
Name: hushhai
Version: 0.0.1
Summary: Internal developer portal for GPU access and resources
Home-page: https://hushh-garage.store/
Author: Yash Makan
Author-email: yash@hushh.ai
License: MIT license
Classifier: Programming Language :: Python :: 3
Classifier: License :: OSI Approved :: MIT License
Classifier: Operating System :: OS Independent
License-File: LICENSE
Requires-Dist: aiohappyeyeballs==2.4.3
Requires-Dist: aiohttp==3.10.10
Requires-Dist: aiosignal==1.3.1
Requires-Dist: annotated-types==0.7.0
Requires-Dist: anyio==4.6.2.post1
Requires-Dist: attrs==24.2.0
Requires-Dist: build==1.2.2.post1
Requires-Dist: certifi==2024.8.30
Requires-Dist: charset-normalizer==3.4.0
Requires-Dist: colorama==0.4.6
Requires-Dist: frozenlist==1.5.0
Requires-Dist: greenlet==3.1.1
Requires-Dist: h11==0.14.0
Requires-Dist: httpcore==1.0.6
Requires-Dist: httpx==0.27.2
Requires-Dist: hushhai==0.0.1
Requires-Dist: idna==3.10
Requires-Dist: jsonpatch==1.33
Requires-Dist: jsonpointer==3.0.0
Requires-Dist: langchain-core==0.3.17
Requires-Dist: langchain-text-splitters==0.3.2
Requires-Dist: langsmith==0.1.142
Requires-Dist: multidict==6.1.0
Requires-Dist: numpy==1.26.4
Requires-Dist: orjson==3.10.11
Requires-Dist: packaging==24.2
Requires-Dist: propcache==0.2.0
Requires-Dist: pydantic==2.9.2
Requires-Dist: pydantic_core==2.23.4
Requires-Dist: pyproject_hooks==1.2.0
Requires-Dist: PyYAML==6.0.2
Requires-Dist: requests==2.32.3
Requires-Dist: requests-toolbelt==1.0.0
Requires-Dist: setuptools==75.4.0
Requires-Dist: sniffio==1.3.1
Requires-Dist: SQLAlchemy==2.0.36
Requires-Dist: tenacity==9.0.0
Requires-Dist: typing_extensions==4.12.2
Requires-Dist: urllib3==2.2.3
Requires-Dist: yarl==1.17.1
